Metadata-Version: 2.1
Name: template-pptx-jinja
Version: 0.2.1
Summary: PowerPoint presentation builder from template using Jinja2
Home-page: https://github.com/Thykof/template-pptx-jinja
Author: Thykof
Author-email: thykof@protonmail.ch
Keywords: powerpoint,ppt,pptx,template
Classifier: Development Status :: 4 - Beta
Classifier: Topic :: Utilities
Classifier: Programming Language :: Python :: 3
Classifier: License :: OSI Approved :: GNU General Public License v3 (GPLv3)
Classifier: Operating System :: OS Independent
License-File: LICENSE
Requires-Dist: jinja2
Requires-Dist: python-pptx
